<?xml version="1.0" encoding="UTF-8"?>
<objects serializationModel="Studio.01.07.00">
    <object class="AudioFile" id="{26175a44-8be3-427b-968e-26cbdf6455fc}">
        <property name="frequencyInKHz">
            <value>44.0999985</value>
        </property>
        <property name="channelCount">
            <value>1</value>
        </property>
        <property name="length">
            <value>0.78070294784580496</value>
        </property>
        <property name="audioFilePath">
            <value>$(AUDIO_BIN_DIR)/Stone2 {2e48b088-c155-43c7-aed7-53ad7e3aea8b}.wav</value>
        </property>
        <relationship name="container">
            <destination>{60c6d670-bb63-43dd-975d-d64782b59524}</destination>
        </relationship>
    </object>
</objects>
